kanidm/__init__.py
kanidm/exceptions.py
kanidm/py.typed
kanidm/types.py
kanidm/utils.py
tests/badssl_trusted_ca.pem
tests/test_authenticate.py
tests/test_config_loader.py
tests/test_radius_token.py
tests/test_session_header.py
tests/test_ssl_ca.py
tests/test_types.py
tests/testutils.py
kanidm-0.0.3.dist-info/WHEEL
kanidm-0.0.3.dist-info/METADATA
kanidm-0.0.3.dist-info/RECORD
