Metadata-Version: 2.1
Name: kanidm
Version: 0.0.3
Summary: Kanidm client library
Home-page: https://kanidm.com/
License: MPL-2.0
Keywords: kanidm,idm,api
Author: James Hodgkinson
Author-email: james@terminaloutcomes.com
Requires-Python: >=3.8,<4.0
Classifier: Development Status :: 3 - Alpha
Classifier: License :: OSI Approved
Classifier: Operating System :: OS Independent
Classifier: Programming Language :: Python :: 3
Classifier: Programming Language :: Python :: 3.10
Classifier: Programming Language :: Python :: 3.8
Classifier: Programming Language :: Python :: 3.9
Requires-Dist: aiohttp (>=3.8.1,<4.0.0)
Requires-Dist: pydantic (>=1.9.2,<2.0.0)
Requires-Dist: toml (>=0.10.2,<0.11.0)
Project-URL: Repository, https://github.com/kanidm/kanidm
